iago/__init__.py
iago/iago.py
iago-0.2.8.dist-info/METADATA
iago-0.2.8.dist-info/WHEEL
iago-0.2.8.dist-info/top_level.txt
iago-0.2.8.dist-info/RECORD
