Metadata-Version: 2.1
Name: iago
Version: 0.2.8
Summary: The package contains your python assistant for Speech Recognition and Text to Speech 
Home-page: https://github.com/lollococce/iago
Author: Lorenzo Coacci
Author-email: lorenzo@coacci.it
License: MIT
Platform: UNKNOWN
Classifier: Programming Language :: Python :: 3
Classifier: License :: OSI Approved :: MIT License
Classifier: Natural Language :: English
Requires-Dist: pandas
Requires-Dist: playsound
Requires-Dist: pyttsx3
Requires-Dist: golog
Requires-Dist: SpeechRecognition
